pangaeapy/__init__.py
pangaeapy/pandataset.py
pangaeapy/panquery.py
pangaeapy/data/parameter_mapping.csv
pangaeapy/exporter/__init__.py
pangaeapy/exporter/pan_dwca_exporter.py
pangaeapy/exporter/pan_exporter.py
pangaeapy/exporter/pan_frictionless_exporter.py
pangaeapy/exporter/pan_netcdf_exporter.py
pangaeapy/exporter/pan_panimport_exporter.py
pangaeapy/exporter/xslt/panmd2eml.xslt
pangaeapy/mappings/__init__.py
pangaeapy/mappings/mapping_helper.py
pangaeapy/mappings/pan_mappings.json
pangaeapy-1.1.0.dist-info/licenses/LICENSE
pangaeapy-1.1.0.dist-info/METADATA
pangaeapy-1.1.0.dist-info/WHEEL
pangaeapy-1.1.0.dist-info/top_level.txt
pangaeapy-1.1.0.dist-info/RECORD
