Metadata-Version: 2.4
Name: pangaeapy
Version: 1.1.0
Summary: Download and analyse (meta-)data of PANGAEA datasets
Author-email: Robert Huber <rhuber@uni-bremen.de>
Project-URL: homepage, https://www.pangaea.de
Project-URL: source, https://github.com/pangaea-data-publisher/pangaeapy
Project-URL: documentation, https://pangaea-data-publisher.github.io/pangaeapy/
Project-URL: issues, https://github.com/pangaea-data-publisher/pangaeapy/issues
Classifier: Development Status :: 5 - Production/Stable
Classifier: Intended Audience :: Science/Research
Classifier: License :: OSI Approved :: GNU General Public License v3 (GPLv3)
Classifier: Operating System :: OS Independent
Classifier: Programming Language :: Python :: 3
Classifier: Programming Language :: Python :: 3 :: Only
Classifier: Programming Language :: Python :: 3.10
Classifier: Programming Language :: Python :: 3.11
Classifier: Programming Language :: Python :: 3.12
Classifier: Programming Language :: Python :: 3.13
Classifier: Topic :: Scientific/Engineering
Requires-Python: >=3.10
License-File: LICENSE
Requires-Dist: aiohttp>=3.11.0
Requires-Dist: lxml>=4.9.3
Requires-Dist: netcdf4>1.6.5
Requires-Dist: numpy>=1.24.4
Requires-Dist: pandas>=2.2.2
Requires-Dist: requests>=2.26.0
Dynamic: license-file
